collective.folderishtraverse-2.0-py3.11-nspkg.pth
collective/folderishtraverse/__init__.py
collective/folderishtraverse/configure.zcml
collective/folderishtraverse/contentmenu.py
collective/folderishtraverse/interfaces.py
collective/folderishtraverse/setuphandlers.py
collective/folderishtraverse/testing.py
collective/folderishtraverse/browser/__init__.py
collective/folderishtraverse/browser/configure.zcml
collective/folderishtraverse/browser/traverse_view.py
collective/folderishtraverse/locales/collective.folderishtraverse.pot
collective/folderishtraverse/locales/merge-plone.pot
collective/folderishtraverse/locales/plone.pot
collective/folderishtraverse/locales/de/LC_MESSAGES/collective.folderishtraverse.po
collective/folderishtraverse/locales/de/LC_MESSAGES/plone.po
collective/folderishtraverse/locales/en/LC_MESSAGES/collective.folderishtraverse.po
collective/folderishtraverse/locales/en/LC_MESSAGES/plone.po
collective/folderishtraverse/locales/zh_CN/LC_MESSAGES/collective.folderishtraverse.po
collective/folderishtraverse/locales/zh_CN/LC_MESSAGES/plone.po
collective/folderishtraverse/profiles/default/browserlayer.xml
collective/folderishtraverse/profiles/default/metadata.xml
collective/folderishtraverse/profiles/default/types.xml
collective/folderishtraverse/profiles/default/types/Folder.xml
collective/folderishtraverse/profiles/default/types/Plone_Site.xml
collective/folderishtraverse/profiles/uninstall/browserlayer.xml
collective/folderishtraverse/tests/__init__.py
collective/folderishtraverse/tests/test_robot.py
collective/folderishtraverse/tests/test_setup.py
collective/folderishtraverse/tests/robot/test_example.robot
collective.folderishtraverse-2.0.dist-info/LICENSE.rst
collective.folderishtraverse-2.0.dist-info/METADATA
collective.folderishtraverse-2.0.dist-info/WHEEL
collective.folderishtraverse-2.0.dist-info/entry_points.txt
collective.folderishtraverse-2.0.dist-info/namespace_packages.txt
collective.folderishtraverse-2.0.dist-info/top_level.txt
collective.folderishtraverse-2.0.dist-info/RECORD
