Metadata-Version: 2.1
Name: collective.folderishtraverse
Version: 2.0
Summary: Traverse to first item in folder
Home-page: http://github.com/collective/collective.forlderishtraverse
Author: Johannes Raggam
Author-email: thetetet@gmail.com
License: GPL
Keywords: plone view
Classifier: Development Status :: 5 - Production/Stable
Classifier: Environment :: Web Environment
Classifier: Framework :: Plone
Classifier: License :: OSI Approved :: GNU General Public License v2 (GPLv2)
Classifier: Operating System :: OS Independent
Classifier: Programming Language :: Python :: 2
Classifier: Programming Language :: Python :: 3
Classifier: Programming Language :: Python
License-File: LICENSE.rst
Requires-Dist: plone.app.contentmenu
Requires-Dist: plone.folder
Requires-Dist: plone.memoize
Requires-Dist: Products.CMFCore
Requires-Dist: Products.CMFPlone
Requires-Dist: Products.statusmessages
Requires-Dist: setuptools
Requires-Dist: zope.component
Requires-Dist: zope.i18nmessageid
Provides-Extra: test
Requires-Dist: plone.app.testing; extra == "test"
Requires-Dist: plone.testing>=5.0.0; extra == "test"
Requires-Dist: plone.app.contenttypes; extra == "test"
Requires-Dist: plone.app.robotframework[debug]; extra == "test"
